py_speech_service/__init__.py
py_speech_service/__main__.py
py_speech_service/downloader.py
py_speech_service/grammar_element.py
py_speech_service/grammar_parser.py
py_speech_service/grpc_server.py
py_speech_service/piper.py
py_speech_service/speaker.py
py_speech_service/speech_recognition.py
py_speech_service/speech_service_pb2.py
py_speech_service/speech_service_pb2_grpc.py
py_speech_service/version.py
py_speech_service-0.1.3.dist-info/METADATA
py_speech_service-0.1.3.dist-info/WHEEL
py_speech_service-0.1.3.dist-info/entry_points.txt
py_speech_service-0.1.3.dist-info/RECORD
