Metadata-Version: 2.1
Name: py-speech-service
Version: 0.1.3
Summary: 
Author: MattEqualsCoder
Author-email: mattequalscoder@gmail.com
Requires-Python: >=3.12,<3.14
Classifier: Programming Language :: Python :: 3
Classifier: Programming Language :: Python :: 3.12
Requires-Dist: asyncio (>=3.4.3,<4.0.0)
Requires-Dist: audioop-lts (==0.2.2) ; python_version >= "3.13" and python_version < "4.0"
Requires-Dist: certifi (>=2025.1.31,<2026.0.0)
Requires-Dist: grpcio (>=1.70.0,<2.0.0)
Requires-Dist: grpcio-tools (>=1.70.0,<2.0.0)
Requires-Dist: num2words (>=0.5.14,<0.6.0)
Requires-Dist: numpy (>=2.2.2,<3.0.0)
Requires-Dist: platformdirs (>=4.3.6,<5.0.0)
Requires-Dist: pyaudio (>=0.2.14,<0.3.0)
Requires-Dist: pydub (>=0.25.1,<0.26.0)
Requires-Dist: pyinstaller (>=6.11.1,<7.0.0)
Requires-Dist: rapidfuzz (>=3.11.0,<4.0.0)
Requires-Dist: sounddevice (>=0.5.1,<0.6.0)
Requires-Dist: vosk (>=0.3.45,<0.4.0)
Requires-Dist: yapper-tts (>=0.2.5,<0.3.0)
